package/__init__.py
package/pidtoo.py
pidtoo-0.0.1.dist-info/LICENSE
pidtoo-0.0.1.dist-info/METADATA
pidtoo-0.0.1.dist-info/WHEEL
pidtoo-0.0.1.dist-info/top_level.txt
pidtoo-0.0.1.dist-info/RECORD
